docs/dqx/src/components/Button.tsx
docs/dqx/src/css/custom.css
docs/dqx/src/pages/index.tsx
databricks/__init__.py
databricks/labs/__init__.py
databricks/labs/dqx/__about__.py
databricks/labs/dqx/__init__.py
databricks/labs/dqx/__main__.py
databricks/labs/dqx/base.py
databricks/labs/dqx/check_funcs.py
databricks/labs/dqx/checks_resolver.py
databricks/labs/dqx/checks_serializer.py
databricks/labs/dqx/checks_storage.py
databricks/labs/dqx/checks_validator.py
databricks/labs/dqx/cli.py
databricks/labs/dqx/config.py
databricks/labs/dqx/config_serializer.py
databricks/labs/dqx/engine.py
databricks/labs/dqx/errors.py
databricks/labs/dqx/executor.py
databricks/labs/dqx/io.py
databricks/labs/dqx/manager.py
databricks/labs/dqx/metrics_listener.py
databricks/labs/dqx/metrics_observer.py
databricks/labs/dqx/rule.py
databricks/labs/dqx/telemetry.py
databricks/labs/dqx/utils.py
databricks/labs/dqx/workflows_runner.py
databricks/labs/dqx/contexts/__init__.py
databricks/labs/dqx/contexts/cli_context.py
databricks/labs/dqx/contexts/global_context.py
databricks/labs/dqx/contexts/workflow_context.py
databricks/labs/dqx/contexts/workspace_context.py
databricks/labs/dqx/dashboards/dashboard.lvdash.json
databricks/labs/dqx/datacontract/__init__.py
databricks/labs/dqx/datacontract/contract_rules_generator.py
databricks/labs/dqx/geo/__init__.py
databricks/labs/dqx/geo/check_funcs.py
databricks/labs/dqx/installer/__init__.py
databricks/labs/dqx/installer/config_provider.py
databricks/labs/dqx/installer/dashboard_installer.py
databricks/labs/dqx/installer/install.py
databricks/labs/dqx/installer/logs.py
databricks/labs/dqx/installer/mixins.py
databricks/labs/dqx/installer/uninstall.py
databricks/labs/dqx/installer/version_checker.py
databricks/labs/dqx/installer/warehouse_installer.py
databricks/labs/dqx/installer/workflow_installer.py
databricks/labs/dqx/installer/workflow_task.py
databricks/labs/dqx/llm/__init__.py
databricks/labs/dqx/llm/llm_core.py
databricks/labs/dqx/llm/llm_engine.py
databricks_labs_dqx-0.12.0.dist-info/METADATA
databricks_labs_dqx-0.12.0.dist-info/WHEEL
databricks_labs_dqx-0.12.0.dist-info/entry_points.txt
databricks_labs_dqx-0.12.0.dist-info/licenses/LICENSE
databricks_labs_dqx-0.12.0.dist-info/licenses/NOTICE
databricks_labs_dqx-0.12.0.dist-info/RECORD
