Metadata-Version: 2.4
Name: databricks-labs-dqx
Version: 0.12.0
Summary: Data Quality eXtended (DQX) is a Python library for data quality checks and data quality monitoring
Project-URL: Issues, https://github.com/databrickslabs/dqx/issues
Project-URL: Source, https://github.com/databrickslabs/dqx
Author-email: Databricks Labs <labs-oss@databricks.com>, Marcin Wojtyczka <marcin.wojtyczka@databricks.com>, Alex Ott <alexey.ott@databricks.com>
Maintainer-email: Databricks Labs <labs-oss@databricks.com>, Marcin Wojtyczka <marcin.wojtyczka@databricks.com>, Alex Ott <alexey.ott@databricks.com>, Greg Hansen <gregory.hansen@databricks.com>
License-File: LICENSE
License-File: NOTICE
Keywords: Databricks
Classifier: Development Status :: 4 - Beta
Classifier: Environment :: Console
Classifier: Framework :: Pytest
Classifier: Intended Audience :: Developers
Classifier: Intended Audience :: System Administrators
Classifier: License :: Other/Proprietary License
Classifier: Operating System :: MacOS
Classifier: Operating System :: Microsoft :: Windows
Classifier: Programming Language :: Python
Classifier: Programming Language :: Python :: 3.10
Classifier: Programming Language :: Python :: 3.11
Classifier: Programming Language :: Python :: 3.12
Classifier: Programming Language :: Python :: Implementation :: CPython
Classifier: Topic :: Software Development :: Libraries
Classifier: Topic :: Utilities
Requires-Python: >=3.10
Requires-Dist: databricks-labs-blueprint<0.10,>=0.9.1
Requires-Dist: databricks-sdk~=0.73
Requires-Dist: pyyaml~=6.0.3
Requires-Dist: sqlalchemy<3.0,>=2.0
Provides-Extra: cli
Requires-Dist: databricks-connect~=15.4; extra == 'cli'
Provides-Extra: datacontract
Requires-Dist: datacontract-cli>=0.11.1; extra == 'datacontract'
Provides-Extra: llm
Requires-Dist: databricks-langchain>=0.1.0; extra == 'llm'
Requires-Dist: dspy~=3.0.3; extra == 'llm'
Requires-Dist: langchain-core>=0.1.0; extra == 'llm'
Provides-Extra: pii
Requires-Dist: numpy<2.0,>=1.20; extra == 'pii'
Requires-Dist: presidio-analyzer~=2.2.359; extra == 'pii'
Requires-Dist: spacy~=3.8; extra == 'pii'
